{"commitInfo":{"timestamp":1724783409455,"operation":"STREAMING UPDATE","operationParameters":{"outputMode":"Append","queryId":"ba4363f2-4b5b-4b77-aca1-97db4b2a7309","epochId":"397"},"readVersion":396,"isolationLevel":"Serializable","isBlindAppend":true,"operationMetrics":{"numRemovedFiles":"0","numOutputRows":"1","numOutputBytes":"2440","numAddedFiles":"1"},"engineInfo":"Apache-Spark/3.5.2 Delta-Lake/3.2.0","txnId":"4613c63e-8da5-4163-abfb-d9ecb96ea248"}}
{"txn":{"appId":"ba4363f2-4b5b-4b77-aca1-97db4b2a7309","version":397,"lastUpdated":1724783409454}}
{"add":{"path":"part-00000-80b1faab-8e47-4426-adf4-78fb18eff01b-c000.snappy.parquet","partitionValues":{},"size":2440,"modificationTime":1724783409446,"dataChange":true,"stats":"{\"numRecords\":1,\"minValues\":{\"TransactionNo\":\"581492\",\"Date\":\"12/9/2019\",\"ProductNo\":\"21967\",\"ProductName\":\"Pack Of 12 Skull Tissues\",\"Price\":6.19,\"Quantity\":1,\"CustomerNo\":15492.0,\"Country\":\"United Kingdom\"},\"maxValues\":{\"TransactionNo\":\"581492\",\"Date\":\"12/9/2019\",\"ProductNo\":\"21967\",\"ProductName\":\"Pack Of 12 Skull Tissues\",\"Price\":6.19,\"Quantity\":1,\"CustomerNo\":15492.0,\"Country\":\"United Kingdom\"},\"nullCount\":{\"TransactionNo\":0,\"Date\":0,\"ProductNo\":0,\"ProductName\":0,\"Price\":0,\"Quantity\":0,\"CustomerNo\":0,\"Country\":0}}"}}
