{"commitInfo":{"timestamp":1724783263309,"operation":"STREAMING UPDATE","operationParameters":{"outputMode":"Append","queryId":"ba4363f2-4b5b-4b77-aca1-97db4b2a7309","epochId":"324"},"readVersion":323,"isolationLevel":"Serializable","isBlindAppend":true,"operationMetrics":{"numRemovedFiles":"0","numOutputRows":"1","numOutputBytes":"2447","numAddedFiles":"1"},"engineInfo":"Apache-Spark/3.5.2 Delta-Lake/3.2.0","txnId":"431a195c-f50a-4e31-acb0-b563ab09506b"}}
{"txn":{"appId":"ba4363f2-4b5b-4b77-aca1-97db4b2a7309","version":324,"lastUpdated":1724783263308}}
{"add":{"path":"part-00000-c824006d-6e00-48fa-96a3-036c721cf416-c000.snappy.parquet","partitionValues":{},"size":2447,"modificationTime":1724783263303,"dataChange":true,"stats":"{\"numRecords\":1,\"minValues\":{\"TransactionNo\":\"581492\",\"Date\":\"12/9/2019\",\"ProductNo\":\"21383\",\"ProductName\":\"Pack Of 12 Sticky Bunnies\",\"Price\":6.19,\"Quantity\":1,\"CustomerNo\":15492.0,\"Country\":\"United Kingdom\"},\"maxValues\":{\"TransactionNo\":\"581492\",\"Date\":\"12/9/2019\",\"ProductNo\":\"21383\",\"ProductName\":\"Pack Of 12 Sticky Bunnies\",\"Price\":6.19,\"Quantity\":1,\"CustomerNo\":15492.0,\"Country\":\"United Kingdom\"},\"nullCount\":{\"TransactionNo\":0,\"Date\":0,\"ProductNo\":0,\"ProductName\":0,\"Price\":0,\"Quantity\":0,\"CustomerNo\":0,\"Country\":0}}"}}
