{"commitInfo":{"timestamp":1724782652749,"operation":"STREAMING UPDATE","operationParameters":{"outputMode":"Append","queryId":"ba4363f2-4b5b-4b77-aca1-97db4b2a7309","epochId":"19"},"readVersion":18,"isolationLevel":"Serializable","isBlindAppend":true,"operationMetrics":{"numRemovedFiles":"0","numOutputRows":"1","numOutputBytes":"2413","numAddedFiles":"1"},"engineInfo":"Apache-Spark/3.5.2 Delta-Lake/3.2.0","txnId":"c1706266-44de-43cc-863a-0667ad7f5e87"}}
{"txn":{"appId":"ba4363f2-4b5b-4b77-aca1-97db4b2a7309","version":19,"lastUpdated":1724782652748}}
{"add":{"path":"part-00000-c25c64e4-d56a-45c6-8bde-79347a958787-c000.snappy.parquet","partitionValues":{},"size":2413,"modificationTime":1724782652742,"dataChange":true,"stats":"{\"numRecords\":1,\"minValues\":{\"TransactionNo\":\"581476\",\"Date\":\"12/9/2019\",\"ProductNo\":\"22998\",\"ProductName\":\"Travel Card Wallet Keep Calm\",\"Price\":10.68,\"Quantity\":72,\"CustomerNo\":12433.0,\"Country\":\"Norway\"},\"maxValues\":{\"TransactionNo\":\"581476\",\"Date\":\"12/9/2019\",\"ProductNo\":\"22998\",\"ProductName\":\"Travel Card Wallet Keep Calm\",\"Price\":10.68,\"Quantity\":72,\"CustomerNo\":12433.0,\"Country\":\"Norway\"},\"nullCount\":{\"TransactionNo\":0,\"Date\":0,\"ProductNo\":0,\"ProductName\":0,\"Price\":0,\"Quantity\":0,\"CustomerNo\":0,\"Country\":0}}"}}
